{
    "users": [
      {
        "id": 1,
        "name": "Abdullahi Ahmed",
        "email": "abdullahiahmed@example.com",
        "username" : "a.ahmed",
        "password" : "dula1996",
        "age": 25,
        "class": "SYMS 6",
        "city": "Mamlö"
      },
      {
        "id": 2,
        "name": "Jane Smith",
        "email": "janesmith@example.com",
        "username": "test",
        "password": "test",
        "age": 30,
        "class": "SYMS 6",
        "city": "Mamlö"
      }
    ]
  }
  